{
  "id": "pneumatics",
  "title": "Pneumatics",
  "summary": "Pneumatic system overview and lessons.",
  "topics": [
    { "id": "general", "title": "General", "type": "lesson", "description": "" },
    { "id": "apu", "title": "APU Bleed System", "type": "lesson", "description": "" },
    { "id": "engine-bleed", "title": "Engine Bleed System", "type": "lesson", "description": "" },
    { "id": "leak-overheat", "title": "Leak/Overheat DET System", "type": "lesson", "description": "" },
    { "id": "quiz", "title": "Quiz", "type": "quiz", "description": "" }
  ]
}